waluigi_facade/__init__.py
waluigi_facade-0.1.0.dist-info/METADATA
waluigi_facade-0.1.0.dist-info/WHEEL
waluigi_facade-0.1.0.dist-info/top_level.txt
waluigi_facade-0.1.0.dist-info/RECORD
